Metadata-Version: 2.4
Name: openfisca-country_template
Version: 8.0.1
Summary: OpenFisca Rules as Code model for Country-Template.
Project-URL: Changelog, https://github.com/openfisca/country-template/blob/main/CHANGELOG.md
Project-URL: Documentation, https://openfisca.org/doc
Project-URL: Homepage, https://github.com/openfisca/country-template
Project-URL: Issues, https://github.com/openfisca/country-template/issues
Project-URL: Repository, https://github.com/openfisca/country-template
Keywords: benefit,microsimulation,rac,rules-as-code,tax
Classifier: Development Status :: 5 - Production/Stable
Classifier: License :: OSI Approved :: GNU Affero General Public License v3
Classifier: Operating System :: POSIX
Classifier: Programming Language :: Python
Classifier: Programming Language :: Python :: 3 :: Only
Classifier: Programming Language :: Python :: 3.9
Classifier: Programming Language :: Python :: 3.10
Classifier: Programming Language :: Python :: 3.11
Classifier: Topic :: Scientific/Engineering :: Information Analysis
Requires-Python: >=3.9
License-File: LICENSE
Requires-Dist: openfisca-core[web-api]>=43
Provides-Extra: dev
Requires-Dist: isort<6,>=5.13.2; extra == "dev"
Requires-Dist: ruff<1,>=0.6.9; extra == "dev"
Requires-Dist: ruff-lsp<1,>=0.0.57; extra == "dev"
Requires-Dist: yamllint>=1.35.1; extra == "dev"
Dynamic: license-file
